sagellm_benchmark/__init__.py
sagellm_benchmark/__init__.pyc
sagellm_benchmark/cli.pyc
sagellm_benchmark/runner.pyc
sagellm_benchmark/traffic.pyc
sagellm_benchmark/types.pyc
sagellm_benchmark/workloads.pyc
sagellm_benchmark/__pycache__/__init__.cpython-311.pyc
sagellm_benchmark/__pycache__/cli.cpython-311.pyc
sagellm_benchmark/__pycache__/metrics.cpython-311.pyc
sagellm_benchmark/__pycache__/runner.cpython-311.pyc
sagellm_benchmark/__pycache__/traffic.cpython-311.pyc
sagellm_benchmark/__pycache__/types.cpython-311.pyc
sagellm_benchmark/__pycache__/workloads.cpython-311.pyc
sagellm_benchmark/clients/__init__.py
sagellm_benchmark/clients/__init__.pyc
sagellm_benchmark/clients/base.pyc
sagellm_benchmark/clients/lmdeploy_client.pyc
sagellm_benchmark/clients/openai_client.pyc
sagellm_benchmark/clients/sagellm_client.pyc
sagellm_benchmark/clients/vllm_client.pyc
sagellm_benchmark/clients/__pycache__/__init__.cpython-311.pyc
sagellm_benchmark/clients/__pycache__/base.cpython-311.pyc
sagellm_benchmark/clients/__pycache__/lmdeploy_client.cpython-311.pyc
sagellm_benchmark/clients/__pycache__/mock.cpython-311.pyc
sagellm_benchmark/clients/__pycache__/openai_client.cpython-311.pyc
sagellm_benchmark/clients/__pycache__/sagellm_client.cpython-311.pyc
sagellm_benchmark/clients/__pycache__/vllm_client.cpython-311.pyc
sagellm_benchmark/datasets/__init__.py
sagellm_benchmark/datasets/__init__.pyc
sagellm_benchmark/datasets/base.pyc
sagellm_benchmark/datasets/random.pyc
sagellm_benchmark/datasets/sharegpt.pyc
sagellm_benchmark/datasets/year_demo.pyc
sagellm_benchmark/datasets/__pycache__/__init__.cpython-311.pyc
sagellm_benchmark/datasets/__pycache__/base.cpython-311.pyc
sagellm_benchmark/datasets/__pycache__/random.cpython-311.pyc
sagellm_benchmark/datasets/__pycache__/sharegpt.cpython-311.pyc
sagellm_benchmark/datasets/__pycache__/year_demo.cpython-311.pyc
sagellm_benchmark/exporters/__init__.py
sagellm_benchmark/exporters/__init__.pyc
sagellm_benchmark/exporters/leaderboard.pyc
isagellm_benchmark-0.4.0.5.dist-info/METADATA
isagellm_benchmark-0.4.0.5.dist-info/WHEEL
isagellm_benchmark-0.4.0.5.dist-info/entry_points.txt
isagellm_benchmark-0.4.0.5.dist-info/top_level.txt
isagellm_benchmark-0.4.0.5.dist-info/RECORD
