Metadata-Version: 2.4
Name: isagellm-benchmark
Version: 0.4.0.5
Summary: Benchmark Suite & E2E Testing for sageLLM
Author-email: IntelliStream Team <shuhao_zhang@hust.edu.cn>
License: Private
Project-URL: Homepage, https://github.com/intellistream/sagellm-benchmark
Project-URL: Repository, https://github.com/intellistream/sagellm-benchmark
Project-URL: Issues, https://github.com/intellistream/sagellm-benchmark/issues
Keywords: llm,inference,benchmark,testing,domestic-hardware
Classifier: Development Status :: 3 - Alpha
Classifier: Intended Audience :: Developers
Classifier: Programming Language :: Python :: 3.10
Classifier: Programming Language :: Python :: 3.11
Requires-Python: ==3.11.*
Requires-Dist: isagellm-protocol<0.5.0,>=0.4.0.0
Requires-Dist: isagellm-core<0.5.0,>=0.4.0.0
Requires-Dist: isagellm-backend<0.5.0,>=0.4.0.1
Requires-Dist: click>=8.0.0
Requires-Dist: rich>=13.0.0
Requires-Dist: datasets>=2.14.0
Requires-Dist: jsonschema>=4.0.0
Provides-Extra: dev
Requires-Dist: pytest>=7.0.0; extra == "dev"
Requires-Dist: pytest-cov>=4.0.0; extra == "dev"
Requires-Dist: pytest-asyncio>=0.21.0; extra == "dev"
Requires-Dist: mypy>=1.0.0; extra == "dev"
Requires-Dist: ruff>=0.1.0; extra == "dev"
Provides-Extra: openai-client
Requires-Dist: openai>=1.0.0; extra == "openai-client"
Provides-Extra: vllm-client
Requires-Dist: vllm>=0.2.0; extra == "vllm-client"
Requires-Dist: openai>=1.0.0; extra == "vllm-client"
Provides-Extra: lmdeploy-client
Requires-Dist: lmdeploy>=0.2.0; extra == "lmdeploy-client"
Requires-Dist: httpx>=0.24.0; extra == "lmdeploy-client"
Provides-Extra: sagellm-client
Requires-Dist: isagellm-backend>=0.3.0.3; extra == "sagellm-client"
Provides-Extra: all-clients
Requires-Dist: openai>=1.0.0; extra == "all-clients"
Requires-Dist: vllm>=0.2.0; extra == "all-clients"
Requires-Dist: lmdeploy>=0.2.0; extra == "all-clients"
Requires-Dist: httpx>=0.24.0; extra == "all-clients"
Requires-Dist: isagellm-backend>=0.3.0.3; extra == "all-clients"
